mbot2/__init__.py
mbot2/boards/__init__.py
mbot2/boards/base/__init__.py
mbot2/boards/mbot2/__init__.py
mbot2/comm/SerialPort/__init__.py
mbot2/comm/SerialPort/test.py
mbot2/comm/mlink/__init__.py
mbot2/ext/__init__.py
mbot2/ext/piano/__init__.py
mbot2/modules/mbot2/__init__.py
mbot2/modules/mbot2/modules.py
mbot2/protocols/PackData.py
mbot2/protocols/Protocols.py
mbot2/protocols/__init__.py
mbot2/utils/__init__.py
mbot2-0.0.2.dist-info/METADATA
mbot2-0.0.2.dist-info/WHEEL
mbot2-0.0.2.dist-info/top_level.txt
mbot2-0.0.2.dist-info/RECORD
