Metadata-Version: 2.1
Name: mbot2
Version: 0.0.2
Summary: libraries for mbot2 platform
Home-page: https://makeblock.com
Author: makeblock
Author-email: flashindream@gmail.com
License: UNKNOWN
Platform: UNKNOWN
Requires-Dist: pyserial
